nonebot_plugin_timed_nickname_updater/__init__.py
nonebot_plugin_timed_nickname_updater-0.1.4.dist-info/LICENSE
nonebot_plugin_timed_nickname_updater-0.1.4.dist-info/METADATA
nonebot_plugin_timed_nickname_updater-0.1.4.dist-info/WHEEL
nonebot_plugin_timed_nickname_updater-0.1.4.dist-info/top_level.txt
nonebot_plugin_timed_nickname_updater-0.1.4.dist-info/RECORD
