Metadata-Version: 2.2
Name: nonebot-plugin-timed-nickname-updater
Version: 0.1.4
Summary: 基于Nonebot2，按时更新群友昵称中日期。
Author-email: StillMisty <1772797842@qq.com>
License:                                  Apache License
Project-URL: Homepage, https://github.com/StillMisty/nonebot_plugin_timed_nickname_updater
Keywords: nonebot2,nonebot,plugin,timed-nickname-updater
Requires-Python: >=3.10
License-File: LICENSE
Requires-Dist: nonebot2>=2.3
Requires-Dist: nonebot-plugin-alconna>=0.54.2
Requires-Dist: nonebot-plugin-apscheduler>=0.5.0
Requires-Dist: nonebot-plugin-localstore>=0.7.3
Requires-Dist: nonebot-adapter-onebot>=2.3
